denpa_finder/__init__.py
denpa_finder/data_source.py
denpa_finder/denpa_finder.py
denpa_finder/query.py
denpa_finder/version.py
denpa_finder-1.0.2.dist-info/METADATA
denpa_finder-1.0.2.dist-info/WHEEL
denpa_finder-1.0.2.dist-info/top_level.txt
denpa_finder-1.0.2.dist-info/RECORD
