Metadata-Version: 2.1
Name: denpa-finder
Version: 1.0.2
Summary: UNKNOWN
Home-page: UNKNOWN
Author: UNKNOWN
Author-email: UNKNOWN
License: UNKNOWN
Platform: UNKNOWN
Requires-Dist: fuzzywuzzy
Requires-Dist: bs4
Requires-Dist: requests
